{
  "recentFiles": [
    {
      "basename": "高阶函数",
      "path": "50 - 卡片知识/51 卡片,概念/Python/高阶函数.md"
    },
    {
      "basename": "Python,概念,卡片",
      "path": "40 - Obsidian/模板/Python,概念,卡片.md"
    },
    {
      "basename": "函数",
      "path": "50 - 卡片知识/51 卡片,概念/Python/函数.md"
    },
    {
      "basename": "Python",
      "path": "50 - 卡片知识/51 卡片,概念/Python/Python.md"
    },
    {
      "basename": "装饰器",
      "path": "50 - 卡片知识/51 卡片,概念/Python/装饰器.md"
    },
    {
      "basename": "闭包",
      "path": "50 - 卡片知识/51 卡片,概念/Python/闭包.md"
    },
    {
      "basename": "00. 主页",
      "path": "40 - Obsidian/主页/00. 主页.md"
    },
    {
      "basename": "第16章 字符串和文本处理",
      "path": "30 - 摘录/33 摘录,书籍/计算机相关/Python参考手册-第4版-修订版/第16章 字符串和文本处理.md"
    },
    {
      "basename": "第6章 函数与函数式编程",
      "path": "30 - 摘录/33 摘录,书籍/计算机相关/Python参考手册-第4版-修订版/第6章 函数与函数式编程.md"
    },
    {
      "basename": "第3章 类型与对象",
      "path": "30 - 摘录/33 摘录,书籍/计算机相关/Python参考手册-第4版-修订版/第3章 类型与对象.md"
    },
    {
      "basename": "2022年05月13日",
      "path": "00 - 每日日记/DailyNote/2022年05月13日.md"
    },
    {
      "basename": "00. 导航",
      "path": "40 - Obsidian/主页/00. 导航.md"
    },
    {
      "basename": "生成器",
      "path": "50 - 卡片知识/51 卡片,概念/Python/生成器.md"
    },
    {
      "basename": "第1章 Python简介",
      "path": "30 - 摘录/33 摘录,书籍/计算机相关/Python参考手册-第4版-修订版/第1章 Python简介.md"
    },
    {
      "basename": "def",
      "path": "50 - 卡片知识/51 卡片,概念/Python/def.md"
    },
    {
      "basename": "2023年02月19日",
      "path": "00 - 每日日记/DailyNote/2023年02月19日.md"
    },
    {
      "basename": "第26章 扩展与嵌入Python",
      "path": "30 - 摘录/33 摘录,书籍/计算机相关/Python参考手册-第4版-修订版/第26章 扩展与嵌入Python.md"
    },
    {
      "basename": "第19章 操作系统服务",
      "path": "30 - 摘录/33 摘录,书籍/计算机相关/Python参考手册-第4版-修订版/第19章 操作系统服务.md"
    },
    {
      "basename": "第12章 内置函数和异常",
      "path": "30 - 摘录/33 摘录,书籍/计算机相关/Python参考手册-第4版-修订版/第12章 内置函数和异常.md"
    },
    {
      "basename": "生成器表达式",
      "path": "50 - 卡片知识/51 卡片,概念/Python/生成器表达式.md"
    },
    {
      "basename": "声明式编程",
      "path": "50 - 卡片知识/51 卡片,概念/Python/声明式编程.md"
    },
    {
      "basename": "函数式编程",
      "path": "50 - 卡片知识/51 卡片,概念/Python/函数式编程.md"
    },
    {
      "basename": "语句",
      "path": "50 - 卡片知识/51 卡片,概念/Python/语句.md"
    },
    {
      "basename": "表达式",
      "path": "50 - 卡片知识/51 卡片,概念/Python/表达式.md"
    },
    {
      "basename": "编译器",
      "path": "50 - 卡片知识/51 卡片,概念/Python/编译器.md"
    },
    {
      "basename": "一等对象",
      "path": "50 - 卡片知识/51 卡片,概念/Python/一等对象.md"
    },
    {
      "basename": "惰性计算",
      "path": "50 - 卡片知识/51 卡片,概念/Python/惰性计算.md"
    },
    {
      "basename": "append",
      "path": "50 - 卡片知识/51 卡片,概念/Python/append.md"
    },
    {
      "basename": "扩展切片",
      "path": "50 - 卡片知识/51 卡片,概念/Python/扩展切片.md"
    },
    {
      "basename": "命令式编程",
      "path": "50 - 卡片知识/51 卡片,概念/Python/命令式编程.md"
    },
    {
      "basename": "ExcaliBrain Snapshot - 2022年12月16日.excalidraw",
      "path": "70 - 构思/75 思维导图/Excalidraw/ExcaliBrain Snapshot - 2022年12月16日.excalidraw.md"
    },
    {
      "basename": "第4章 运算符与表达式",
      "path": "30 - 摘录/33 摘录,书籍/计算机相关/Python参考手册-第4版-修订版/第4章 运算符与表达式.md"
    },
    {
      "basename": "列表推导",
      "path": "50 - 卡片知识/51 卡片,概念/Python/列表推导.md"
    },
    {
      "basename": "迭代器",
      "path": "50 - 卡片知识/51 卡片,概念/Python/迭代器.md"
    },
    {
      "basename": "Anaconda",
      "path": "40 - Obsidian/41 参考/41-1 参考,软件工具/Anaconda.md"
    },
    {
      "basename": "第24章 网络数据处理和编码",
      "path": "30 - 摘录/33 摘录,书籍/计算机相关/Python参考手册-第4版-修订版/第24章 网络数据处理和编码.md"
    },
    {
      "basename": "第21章 网络编程和套接字",
      "path": "30 - 摘录/33 摘录,书籍/计算机相关/Python参考手册-第4版-修订版/第21章 网络编程和套接字.md"
    },
    {
      "basename": "第20章 线程与并发",
      "path": "30 - 摘录/33 摘录,书籍/计算机相关/Python参考手册-第4版-修订版/第20章 线程与并发.md"
    },
    {
      "basename": "第15章 数据结构、算法与代码简化",
      "path": "30 - 摘录/33 摘录,书籍/计算机相关/Python参考手册-第4版-修订版/第15章 数据结构、算法与代码简化.md"
    },
    {
      "basename": "2023年01月11日",
      "path": "00 - 每日日记/DailyNote/2023年01月11日.md"
    },
    {
      "basename": "2023年01月03日",
      "path": "00 - 每日日记/DailyNote/2023年01月03日.md"
    },
    {
      "basename": "51 卡片,概念",
      "path": "50 - 卡片知识/51 卡片,概念/51 卡片,概念.md"
    },
    {
      "basename": "第14章 数学运算",
      "path": "30 - 摘录/33 摘录,书籍/计算机相关/Python参考手册-第4版-修订版/第14章 数学运算.md"
    },
    {
      "basename": "第7章 类与面向对象编程",
      "path": "30 - 摘录/33 摘录,书籍/计算机相关/Python参考手册-第4版-修订版/第7章 类与面向对象编程.md"
    },
    {
      "basename": "第5章 程序结构与控制流",
      "path": "30 - 摘录/33 摘录,书籍/计算机相关/Python参考手册-第4版-修订版/第5章 程序结构与控制流.md"
    },
    {
      "basename": "从类型到网络：建筑智能设计的知识表征方法综述",
      "path": "30 - 摘录/31 摘录,文献/建筑智能/从类型到网络：建筑智能设计的知识表征方法综述.md"
    },
    {
      "basename": "浅复制",
      "path": "50 - 卡片知识/51 卡片,概念/Python/浅复制.md"
    },
    {
      "basename": "生成器函数",
      "path": "50 - 卡片知识/51 卡片,概念/Python/生成器函数.md"
    },
    {
      "basename": "yield",
      "path": "50 - 卡片知识/51 卡片,概念/Python/yield.md"
    },
    {
      "basename": "for",
      "path": "50 - 卡片知识/51 卡片,概念/Python/for.md"
    }
  ],
  "omittedPaths": [],
  "maxLength": null
}